condoor/__init__.py
condoor/accountmgr.py
condoor/exceptions.py
condoor/hopinfo.py
condoor/utils.py
condoor/controllers/__init__.py
condoor/controllers/fsm.py
condoor/controllers/pexpect_ctrl.py
condoor/controllers/protocols/__init__.py
condoor/controllers/protocols/base.py
condoor/controllers/protocols/ssh.py
condoor/controllers/protocols/telnet.py
condoor/platforms/__init__.py
condoor/platforms/ASR9K.py
condoor/platforms/generic.py
condoor/platforms/IOS.py
condoor/platforms/NCS6K.py
condoor/platforms/NX-OS.py
condoor-0.1.6.dist-info/DESCRIPTION.rst
condoor-0.1.6.dist-info/METADATA
condoor-0.1.6.dist-info/metadata.json
condoor-0.1.6.dist-info/RECORD
condoor-0.1.6.dist-info/top_level.txt
condoor-0.1.6.dist-info/WHEEL
condoor-0.1.6.dist-info/zip-safe
